setup.py
django_site_skins.egg-info/PKG-INFO
django_site_skins.egg-info/SOURCES.txt
django_site_skins.egg-info/dependency_links.txt
django_site_skins.egg-info/top_level.txt
skins/__init__.py
skins/config.py
skins/context_processors.py
skins/loader.py
skins/models.py
skins/skin.py
skins/tests.py
skins/utils.py
skins/templatetags/__init__.py
skins/templatetags/skin_tags.py