Metadata-Version: 1.0
Name: django-site-skins
Version: 0.1-1
Summary: site-skins
Home-page: http://bitbucket.org/bkroeze/django-site-skins/
Author: Bruce Kroeze
Author-email: bruce@ecomsmith.com
License: New BSD License
Platform: any
Classifier: Development Status :: 4 - Beta
Classifier: Environment :: Web Environment
Classifier: Framework :: Django
Classifier: Intended Audience :: Developers
Classifier: License :: OSI Approved :: BSD License
Classifier: Operating System :: OS Independent
Classifier: Programming Language :: Python
